anytree/__init__.py
anytree/cachedsearch.py
anytree/config.py
anytree/dotexport.py
anytree/exporter/__init__.py
anytree/exporter/dictexporter.py
anytree/exporter/dotexporter.py
anytree/exporter/jsonexporter.py
anytree/exporter/mermaidexporter.py
anytree/importer/__init__.py
anytree/importer/dictimporter.py
anytree/importer/jsonimporter.py
anytree/iterators/__init__.py
anytree/iterators/abstractiter.py
anytree/iterators/levelordergroupiter.py
anytree/iterators/levelorderiter.py
anytree/iterators/postorderiter.py
anytree/iterators/preorderiter.py
anytree/iterators/zigzaggroupiter.py
anytree/node/__init__.py
anytree/node/anynode.py
anytree/node/exceptions.py
anytree/node/lightnodemixin.py
anytree/node/node.py
anytree/node/nodemixin.py
anytree/node/symlinknode.py
anytree/node/symlinknodemixin.py
anytree/node/util.py
anytree/render.py
anytree/resolver.py
anytree/search.py
anytree/util/__init__.py
anytree/walker.py
anytree-2.12.0.dist-info/LICENSE
anytree-2.12.0.dist-info/METADATA
anytree-2.12.0.dist-info/WHEEL
anytree-2.12.0.dist-info/RECORD
