Metadata-Version: 2.1
Name: anytree
Version: 2.12.0
Summary: Powerful and Lightweight Python Tree Data Structure with various plugins
License: Apache-2.0
Keywords: tree,tree data,treelib,tree walk,tree structure
Author: c0fec0de
Author-email: c0fec0de@gmail.com
Requires-Python: >=3.7.2,<4
Classifier: Development Status :: 5 - Production/Stable
Classifier: License :: OSI Approved :: Apache Software License
Classifier: Programming Language :: Python :: 3
Classifier: Programming Language :: Python :: 3.8
Classifier: Programming Language :: Python :: 3.9
Classifier: Programming Language :: Python :: 3.10
Classifier: Programming Language :: Python :: 3.11
Classifier: Programming Language :: Python :: 3.12
Classifier: Programming Language :: Python :: 3.7
Classifier: Topic :: Software Development :: Libraries :: Python Modules
Requires-Dist: six
